LICENSE
README.rst
setup.py
django_pdf_tables.egg-info/PKG-INFO
django_pdf_tables.egg-info/SOURCES.txt
django_pdf_tables.egg-info/dependency_links.txt
django_pdf_tables.egg-info/requires.txt
django_pdf_tables.egg-info/top_level.txt
pdf_tables/__init__.py
pdf_tables/colors.py
pdf_tables/mixins.py
pdf_tables/views.py